simplecachebz2/__init__.py
simplecachebz2/spec.py
fsspec_bz2-0.1.2.dist-info/METADATA
fsspec_bz2-0.1.2.dist-info/WHEEL
fsspec_bz2-0.1.2.dist-info/entry_points.txt
fsspec_bz2-0.1.2.dist-info/top_level.txt
fsspec_bz2-0.1.2.dist-info/RECORD
