Metadata-Version: 2.1
Name: fsspec-bz2
Version: 0.1.2
Summary: Adds BZ2 Support to simplecache
Requires-Python: >=3.11
Requires-Dist: fsspec ==2024.2.0
